olab_prediction_market_sdk/__init__.py
olab_prediction_market_sdk/config.py
olab_prediction_market_sdk/model.py
olab_prediction_market_sdk/sdk.py
olab_prediction_market_sdk/chain/__init__.py
olab_prediction_market_sdk/chain/contract_caller.py
olab_prediction_market_sdk/chain/exception.py
olab_prediction_market_sdk/chain/contracts/__init__.py
olab_prediction_market_sdk/chain/contracts/conditional_tokens.py
olab_prediction_market_sdk/chain/contracts/erc20.py
olab_prediction_market_sdk/chain/py_order_utils/__init__.py
olab_prediction_market_sdk/chain/py_order_utils/constants.py
olab_prediction_market_sdk/chain/py_order_utils/signer.py
olab_prediction_market_sdk/chain/py_order_utils/utils.py
olab_prediction_market_sdk/chain/py_order_utils/builders/__init__.py
olab_prediction_market_sdk/chain/py_order_utils/builders/base_builder.py
olab_prediction_market_sdk/chain/py_order_utils/builders/exception.py
olab_prediction_market_sdk/chain/py_order_utils/builders/order_builder.py
olab_prediction_market_sdk/chain/py_order_utils/builders/order_builder_test.py
olab_prediction_market_sdk/chain/py_order_utils/model/__init__.py
olab_prediction_market_sdk/chain/py_order_utils/model/order.py
olab_prediction_market_sdk/chain/py_order_utils/model/order_type.py
olab_prediction_market_sdk/chain/py_order_utils/model/sides.py
olab_prediction_market_sdk/chain/py_order_utils/model/signatures.py
olab_prediction_market_sdk/chain/safe/__init__.py
olab_prediction_market_sdk/chain/safe/constants.py
olab_prediction_market_sdk/chain/safe/enums.py
olab_prediction_market_sdk/chain/safe/exceptions.py
olab_prediction_market_sdk/chain/safe/multisend.py
olab_prediction_market_sdk/chain/safe/safe.py
olab_prediction_market_sdk/chain/safe/safe_signature.py
olab_prediction_market_sdk/chain/safe/safe_test.py
olab_prediction_market_sdk/chain/safe/safe_tx.py
olab_prediction_market_sdk/chain/safe/signatures.py
olab_prediction_market_sdk/chain/safe/typing.py
olab_prediction_market_sdk/chain/safe/utils.py
olab_prediction_market_sdk-0.1.1.dist-info/METADATA
olab_prediction_market_sdk-0.1.1.dist-info/WHEEL
olab_prediction_market_sdk-0.1.1.dist-info/top_level.txt
olab_prediction_market_sdk-0.1.1.dist-info/RECORD
